SmartApi/__init__.py
SmartApi/smartApiWebsocket.py
SmartApi/smartConnect.py
SmartApi/smartExceptions.py
SmartApi/smartWebSocketOrderUpdate.py
SmartApi/smartWebSocketV2.py
SmartApi/version.py
SmartApi/webSocket.py
test/__init__.py
test/api_test.py
test/testcases.py
smartapi_python-1.5.4.dist-info/METADATA
smartapi_python-1.5.4.dist-info/WHEEL
smartapi_python-1.5.4.dist-info/top_level.txt
smartapi_python-1.5.4.dist-info/RECORD
