Metadata-Version: 2.1
Name: smartapi-python
Version: 1.5.4
Summary: Angel Broking openApi integration
Home-page: https://github.com/angelbroking-github/smartapi-python
Author: ab-smartapi
Author-email: smartapi.sdk@gmail.com
Classifier: Development Status :: 5 - Production/Stable
Classifier: Intended Audience :: Developers
Classifier: Intended Audience :: Financial and Insurance Industry
Classifier: Programming Language :: Python
Classifier: Natural Language :: English
Classifier: Programming Language :: Python :: 2.7
Classifier: Programming Language :: Python :: 3.5
Classifier: Programming Language :: Python :: 3.6
Classifier: Programming Language :: Python :: 3.7
Classifier: Topic :: Office/Business :: Financial :: Investment
Classifier: Topic :: Software Development :: Libraries :: Python Modules
Classifier: Topic :: Software Development :: Libraries
Requires-Dist: requests >=2.18.4
Requires-Dist: six >=1.11.0
Requires-Dist: python-dateutil >=2.6.1
